[
  {
    "code": "QHI",
    "name": "Đại học Công nghệ - ĐHQGHN (UET)",
    "scale": 30,
    "majors": [
      { "major_name": "Công nghệ thông tin", "blocks": ["A00", "A01", "D01"], "score_2025": 28.19 },
      { "major_name": "Khoa học máy tính", "blocks": ["A00", "A01", "D01"], "score_2025": 27.86 },
      { "major_name": "Trí tuệ nhân tạo", "blocks": ["A00", "A01", "D01"], "score_2025": 27.75 },
      { "major_name": "Khoa học dữ liệu", "blocks": ["A00", "A01", "D01"], "score_2025": 27.38 },
      { "major_name": "Kỹ thuật máy tính", "blocks": ["A00", "A01", "D01"], "score_2025": 27.00 },
      { "major_name": "Kỹ thuật điều khiển và tự động hóa", "blocks": ["A00", "A01", "D01"], "score_2025": 27.90 },
      { "major_name": "Công nghệ kỹ thuật cơ điện tử", "blocks": ["A00", "A01", "D01"], "score_2025": 26.73 },
      { "major_name": "Mạng máy tính và truyền thông dữ liệu", "blocks": ["A00", "A01", "D01"], "score_2025": 26.73 },
      { "major_name": "Công nghệ kỹ thuật điện tử - Viễn thông", "blocks": ["A00", "A01", "D01"], "score_2025": 26.63 },
      { "major_name": "Hệ thống thông tin", "blocks": ["A00", "A01", "D01"], "score_2025": 26.38 },
      { "major_name": "Cơ kỹ thuật", "blocks": ["A00", "A01", "D01"], "score_2025": 26.15 },
      { "major_name": "Kỹ thuật Robot", "blocks": ["A00", "A01", "D01"], "score_2025": 26.00 },
      { "major_name": "Công nghệ vật liệu", "blocks": ["A00", "A01", "D01"], "score_2025": 25.60 },
      { "major_name": "Vật lý kỹ thuật", "blocks": ["A00", "A01", "D01"], "score_2025": 25.20 },
      { "major_name": "Kỹ thuật năng lượng", "blocks": ["A00", "A01", "D01"], "score_2025": 24.87 },
      { "major_name": "Thiết kế công nghiệp và Đồ họa", "blocks": ["A00", "A01", "D01"], "score_2025": 24.20 },
      { "major_name": "Công nghệ hàng không vũ trụ", "blocks": ["A00", "A01", "D01"], "score_2025": 23.96 },
      { "major_name": "Công nghệ kỹ thuật xây dựng", "blocks": ["A00", "A01", "D01"], "score_2025": 22.25 },
      { "major_name": "Công nghệ sinh học", "blocks": ["A00", "A01", "B00"], "score_2025": 22.13 },
      { "major_name": "Công nghệ nông nghiệp", "blocks": ["A00", "A01", "B00"], "score_2025": 22.00 }
    ]
  },
  {
    "code": "BKA",
    "name": "Đại học Bách Khoa Hà Nội (HUST)",
    "scale": 30,
    "majors": [
      { "major_name": "Khoa học dữ liệu và Trí tuệ nhân tạo (CT tiên tiến)", "blocks": ["A00", "A01"], "score_2025": 29.39 },
      { "major_name": "CNTT: Khoa học Máy tính", "blocks": ["A00", "A01"], "score_2025": 29.19 },
      { "major_name": "CNTT: Kỹ thuật Máy tính", "blocks": ["A00", "A01"], "score_2025": 28.83 },
      { "major_name": "An toàn không gian số - Cyber Security (CT Tiên tiến)", "blocks": ["A00", "A01"], "score_2025": 28.69 },
      { "major_name": "Công nghệ thông tin (Global ICT)", "blocks": ["A00", "A01"], "score_2025": 28.66 },
      { "major_name": "Kỹ thuật Điều khiển - Tự động hoá", "blocks": ["A00", "A01"], "score_2025": 28.48 },
      { "major_name": "Kỹ thuật Vi điện tử và Công nghệ nano", "blocks": ["A00", "A01", "D07"], "score_2025": 28.25 },
      { "major_name": "Kỹ thuật Điều khiển - Tự động hoá (CT tiên tiến)", "blocks": ["A00", "A01"], "score_2025": 28.12 },
      { "major_name": "Kỹ thuật Điện tử - Viễn thông", "blocks": ["A00", "A01"], "score_2025": 28.07 },
      { "major_name": "Công nghệ thông tin (Việt - Nhật)", "blocks": ["A00", "A01"], "score_2025": 27.97 },
      { "major_name": "Kỹ thuật Cơ điện tử", "blocks": ["A00", "A01"], "score_2025": 27.90 },
      { "major_name": "Công nghệ thông tin (Việt - Pháp)", "blocks": ["A00", "A01"], "score_2025": 27.83 },
      { "major_name": "Toán - Tin", "blocks": ["A00", "A01"], "score_2025": 27.80 },
      { "major_name": "Hệ thống thông tin quản lý", "blocks": ["A00", "A01"], "score_2025": 27.72 },
      { "major_name": "Kỹ thuật Điện", "blocks": ["A00", "A01"], "score_2025": 27.55 },
      { "major_name": "Kỹ thuật Điện tử - Viễn thông (CT tiên tiến)", "blocks": ["A00", "A01"], "score_2025": 27.55 },
      { "major_name": "Tin học công nghiệp và Tự động hóa (PFIEV)", "blocks": ["A00", "A01"], "score_2025": 27.27 },
      { "major_name": "Kỹ thuật Ô tô", "blocks": ["A00", "A01"], "score_2025": 27.03 },
      { "major_name": "Kỹ thuật Cơ điện tử (CT tiên tiến)", "blocks": ["A00", "A01"], "score_2025": 26.74 },
      { "major_name": "Kỹ thuật Cơ khí", "blocks": ["A00", "A01"], "score_2025": 26.62 },
      { "major_name": "Truyền thông số và Kỹ thuật đa phương tiện (CT tiên tiến)", "blocks": ["A00", "A01"], "score_2025": 26.62 },
      { "major_name": "Kỹ thuật Hàng không", "blocks": ["A00", "A01"], "score_2025": 26.60 },
      { "major_name": "Hệ thống điện và năng lượng tái tạo (CT tiên tiến)", "blocks": ["A00", "A01"], "score_2025": 26.56 },
      { "major_name": "Vật lý kỹ thuật", "blocks": ["A00", "A01"], "score_2025": 26.41 },
      { "major_name": "Kỹ thuật Y sinh", "blocks": ["A00", "A01", "B00"], "score_2025": 26.32 },
      { "major_name": "Kỹ thuật Cơ khí động lực", "blocks": ["A00", "A01"], "score_2025": 26.25 },
      { "major_name": "Kỹ thuật Y sinh (CT tiên tiến)", "blocks": ["A00", "A01"], "score_2025": 25.58 },
      { "major_name": "Kỹ thuật Nhiệt", "blocks": ["A00", "A01"], "score_2025": 25.47 },
      { "major_name": "Kỹ thuật Vật liệu", "blocks": ["A00", "A01", "D07"], "score_2025": 25.39 },
      { "major_name": "Tiếng Trung KHKT và Công nghệ", "blocks": ["D01", "D04"], "score_2025": 25.36 },
      { "major_name": "Kỹ thuật Ô tô (CT tiên tiến)", "blocks": ["A00", "A01"], "score_2025": 25.18 },
      { "major_name": "Công nghệ vật liệu Polyme và Compozit", "blocks": ["A00", "A01", "D07"], "score_2025": 25.16 },
      { "major_name": "Kỹ thuật hạt nhân", "blocks": ["A00", "A01", "A02"], "score_2025": 25.07 },
      { "major_name": "Tài chính - Ngân hàng", "blocks": ["A00", "A01", "D01"], "score_2025": 24.80 },
      { "major_name": "Quản trị kinh doanh", "blocks": ["A00", "A01", "D01"], "score_2025": 24.80 },
      { "major_name": "Tiếng Anh KHKT và Công nghệ", "blocks": ["D01"], "score_2025": 24.80 },
      { "major_name": "Kế toán", "blocks": ["A00", "A01", "D01"], "score_2025": 24.63 },
      { "major_name": "Quản lý công nghiệp", "blocks": ["A00", "A01", "D01"], "score_2025": 24.40 },
      { "major_name": "Logistics và Quản lý chuỗi cung ứng (CT tiên tiến)", "blocks": ["A01", "D01"], "score_2025": 24.21 },
      { "major_name": "Kỹ thuật in", "blocks": ["A00", "A01", "D07"], "score_2025": 24.06 },
      { "major_name": "Kỹ thuật Hoá học", "blocks": ["A00", "B00", "D07"], "score_2025": 24.05 },
      { "major_name": "Kỹ thuật Thực phẩm", "blocks": ["A00", "B00", "D07"], "score_2025": 23.38 },
      { "major_name": "Hoá học", "blocks": ["A00", "B00", "D07"], "score_2025": 23.19 },
      { "major_name": "Kỹ thuật Sinh học", "blocks": ["A00", "B00", "D07"], "score_2025": 23.02 },
      { "major_name": "Công nghệ Dệt - May", "blocks": ["A00", "A01", "D07"], "score_2025": 22.48 },
      { "major_name": "Kỹ thuật Môi trường", "blocks": ["A00", "B00", "D07"], "score_2025": 22.22 },
      { "major_name": "Quản lý Tài nguyên và Môi trường", "blocks": ["A00", "B00", "D07"], "score_2025": 21.53 },
      { "major_name": "Khoa học máy tính - hợp tác với ĐH Troy (Hoa Kỳ)", "blocks": ["A00", "A01", "D01"], "score_2025": 21.80 }
    ]
  },
  {
    "code": "BVH",
    "name": "Học viện Công nghệ Bưu chính Viễn thông phía Bắc (PTIT)",
    "scale": 30,
    "majors": [
      { "major_name": "Khoa học máy tính (định hướng Khoa học dữ liệu)", "blocks": ["A00", "A01"], "score_2025": 26.21 },
      { "major_name": "Kỹ thuật Điều khiển và tự động hóa", "blocks": ["A00", "A01"], "score_2025": 26.19 },
      { "major_name": "Công nghệ thông tin", "blocks": ["A00", "A01"], "score_2025": 25.80 },
      { "major_name": "Trí tuệ nhân tạo", "blocks": ["A00", "A01"], "score_2025": 25.67 },
      { "major_name": "Công nghệ vi mạch bán dẫn", "blocks": ["A00", "A01"], "score_2025": 25.50 },
      { "major_name": "Truyền thông đa phương tiện", "blocks": ["A00", "A01", "D01"], "score_2025": 25.25 },
      { "major_name": "An toàn thông tin", "blocks": ["A00", "A01"], "score_2025": 25.21 },
      { "major_name": "Kỹ thuật Điện tử viễn thông", "blocks": ["A00", "A01"], "score_2025": 25.10 },
      { "major_name": "Thương mại điện tử", "blocks": ["A00", "A01", "D01"], "score_2025": 25.10 },
      { "major_name": "Trí tuệ nhân tạo vạn vật (AIoT)", "blocks": ["A00", "A01"], "score_2025": 24.87 },
      { "major_name": "Công nghệ Kỹ thuật Điện, điện tử", "blocks": ["A00", "A01"], "score_2025": 24.61 },
      { "major_name": "Kỹ thuật dữ liệu", "blocks": ["A00", "A01"], "score_2025": 24.40 },
      { "major_name": "Logistics và quản trị chuỗi cung ứng", "blocks": ["A00", "A01", "D01"], "score_2025": 24.20 },
      { "major_name": "Công nghệ đa phương tiện", "blocks": ["A00", "A01", "D01"], "score_2025": 24.00 },
      { "major_name": "Marketing", "blocks": ["A00", "A01", "D01"], "score_2025": 24.00 },
      { "major_name": "Công nghệ tài chính (Fintech)", "blocks": ["A00", "A01", "D01"], "score_2025": 23.63 },
      { "major_name": "Công nghệ thông tin - Chất lượng cao", "blocks": ["A00", "A01"], "score_2025": 23.60 },
      { "major_name": "Thiết kế và phát triển Game", "blocks": ["A00", "A01", "D01"], "score_2025": 23.48 },
      { "major_name": "Công nghệ thông tin Việt - Nhật", "blocks": ["A00", "A01"], "score_2025": 23.48 },
      { "major_name": "Quan hệ công chúng", "blocks": ["A00", "A01", "D01"], "score_2025": 23.47 },
      { "major_name": "An toàn thông tin - Chất lượng cao", "blocks": ["A00", "A01"], "score_2025": 23.14 },
      { "major_name": "Quản trị kinh doanh", "blocks": ["A00", "A01", "D01"], "score_2025": 22.75 },
      { "major_name": "Báo chí", "blocks": ["A00", "A01", "D01"], "score_2025": 22.67 },
      { "major_name": "Kế toán", "blocks": ["A00", "A01", "D01"], "score_2025": 22.50 },
      { "major_name": "Công nghệ thông tin (Cử nhân định hướng ứng dụng)", "blocks": ["A00", "A01"], "score_2025": 22.20 }
    ]
  },
  {
    "code": "QHT",
    "name": "Đại học Khoa học Tự nhiên - ĐHQGHN (HUS)",
    "scale": 30,
    "majors": [
      { "major_name": "Khoa học dữ liệu", "blocks": ["A00", "A01", "D07"], "score_2025": 26.00 },
      { "major_name": "Toán học", "blocks": ["A00", "A01", "D07"], "score_2025": 25.90 },
      { "major_name": "Công nghệ Bán dẫn", "blocks": ["A00", "A01", "D07"], "score_2025": 25.55 },
      { "major_name": "Toán tin", "blocks": ["A00", "A01", "D07"], "score_2025": 25.50 },
      { "major_name": "Khoa học máy tính và thông tin", "blocks": ["A00", "A01", "D07"], "score_2025": 25.35 },
      { "major_name": "Vật lý học", "blocks": ["A00", "A01", "D07"], "score_2025": 24.65 },
      { "major_name": "Kỹ thuật điện tử và tin học", "blocks": ["A00", "A01", "D07"], "score_2025": 24.57 },
      { "major_name": "Khoa học vật liệu", "blocks": ["A00", "A01", "D07"], "score_2025": 24.20 },
      { "major_name": "Địa lý tự nhiên", "blocks": ["A00", "A01", "B00"], "score_2025": 23.95 },
      { "major_name": "Hoá học", "blocks": ["A00", "B00", "D07"], "score_2025": 23.90 },
      { "major_name": "Hoá dược", "blocks": ["A00", "B00", "D07"], "score_2025": 23.70 },
      { "major_name": "Khoa học thông tin địa không gian", "blocks": ["A00", "A01", "B00"], "score_2025": 23.50 },
      { "major_name": "Công nghệ kỹ thuật hạt nhân", "blocks": ["A00", "A01", "D07"], "score_2025": 23.50 },
      { "major_name": "Công nghệ kỹ thuật hoá học", "blocks": ["A00", "B00", "D07"], "score_2025": 23.45 },
      { "major_name": "Quản lý phát triển đô thị và bất động sản", "blocks": ["A00", "A01", "D01"], "score_2025": 22.90 },
      { "major_name": "Khí tượng và khí hậu học", "blocks": ["A00", "A01", "B00"], "score_2025": 22.80 },
      { "major_name": "Khoa học và công nghệ thực phẩm", "blocks": ["A00", "B00", "D07"], "score_2025": 22.80 },
      { "major_name": "Quản lý đất đai", "blocks": ["A00", "A01", "B00", "D01"], "score_2025": 22.27 },
      { "major_name": "Quản lý tài nguyên và môi trường", "blocks": ["A00", "A01", "B00", "D01"], "score_2025": 22.20 },
      { "major_name": "Công nghệ sinh học", "blocks": ["B00", "B08", "D07"], "score_2025": 22.05 },
      { "major_name": "Địa chất học", "blocks": ["A00", "A01", "B00"], "score_2025": 22.05 },
      { "major_name": "Công nghệ kỹ thuật môi trường", "blocks": ["A00", "B00", "D07"], "score_2025": 21.55 },
      { "major_name": "Hải dương học", "blocks": ["A00", "A01", "B00"], "score_2025": 21.50 },
      { "major_name": "Khoa học môi trường", "blocks": ["A00", "B00", "D07"], "score_2025": 21.25 },
      { "major_name": "Môi trường, sức khỏe và an toàn", "blocks": ["A00", "B00", "D07"], "score_2025": 21.20 },
      { "major_name": "Tài nguyên và môi trường nước", "blocks": ["A00", "A01", "B00"], "score_2025": 21.10 },
      { "major_name": "Sinh dược học", "blocks": ["B00", "D07"], "score_2025": 20.10 },
      { "major_name": "Sinh học", "blocks": ["B00", "D07"], "score_2025": 20.05 }
    ]
  },
  {
    "code": "DCN",
    "name": "Đại học Công nghiệp Hà Nội (HAUI)",
    "scale": 30,
    "majors": [
      { "major_name": "Công nghệ kỹ thuật điều khiển và tự động hóa", "blocks": ["A00", "A01"], "score_2025": 26.27 },
      { "major_name": "Công nghệ kỹ thuật cơ điện tử", "blocks": ["A00", "A01"], "score_2025": 25.17 },
      { "major_name": "Robot và trí tuệ nhân tạo", "blocks": ["A00", "A01"], "score_2025": 24.30 },
      { "major_name": "Công nghệ kỹ thuật điện, điện tử", "blocks": ["A00", "A01"], "score_2025": 23.93 },
      { "major_name": "Công nghệ kỹ thuật cơ điện tử ô tô", "blocks": ["A00", "A01"], "score_2025": 23.93 },
      { "major_name": "Khoa học máy tính", "blocks": ["A00", "A01"], "score_2025": 23.72 },
      { "major_name": "Công nghệ kỹ thuật cơ khí", "blocks": ["A00", "A01"], "score_2025": 23.72 },
      { "major_name": "An toàn thông tin", "blocks": ["A00", "A01"], "score_2025": 23.43 },
      { "major_name": "Công nghệ thông tin", "blocks": ["A00", "A01"], "score_2025": 23.09 },
      { "major_name": "Ngôn ngữ Trung Quốc", "blocks": ["D01", "D04"], "score_2025": 23.00 },
      { "major_name": "Logistics và quản lý chuỗi cung ứng", "blocks": ["A01", "D01"], "score_2025": 22.76 },
      { "major_name": "Công nghệ kỹ thuật điện tử - viễn thông", "blocks": ["A00", "A01"], "score_2025": 22.75 },
      { "major_name": "Marketing", "blocks": ["A01", "D01"], "score_2025": 22.50 },
      { "major_name": "Công nghệ kỹ thuật ô tô", "blocks": ["A00", "A01"], "score_2025": 22.50 },
      { "major_name": "Kỹ thuật cơ khí động lực", "blocks": ["A00", "A01"], "score_2025": 22.50 },
      { "major_name": "Công nghệ kỹ thuật khuôn mẫu", "blocks": ["A00", "A01"], "score_2025": 22.50 },
      { "major_name": "Kỹ thuật sản xuất thông minh", "blocks": ["A00", "A01"], "score_2025": 22.50 },
      { "major_name": "Công nghệ đa phương tiện", "blocks": ["A00", "A01"], "score_2025": 22.25 },
      { "major_name": "Quản trị dịch vụ du lịch và lữ hành", "blocks": ["D01"], "score_2025": 22.25 },
      { "major_name": "Công nghệ kỹ thuật máy tính", "blocks": ["A00", "A01"], "score_2025": 21.85 },
      { "major_name": "Công nghệ kỹ thuật nhiệt", "blocks": ["A00", "A01"], "score_2025": 21.85 },
      { "major_name": "Du lịch", "blocks": ["D01"], "score_2025": 21.85 },
      { "major_name": "Kỹ thuật phần mềm", "blocks": ["A00", "A01"], "score_2025": 21.75 },
      { "major_name": "Kỹ thuật hệ thống công nghiệp", "blocks": ["A00", "A01"], "score_2025": 21.75 },
      { "major_name": "Quản trị khách sạn", "blocks": ["D01"], "score_2025": 21.75 },
      { "major_name": "Mạng máy tính và truyền thông dữ liệu", "blocks": ["A00", "A01"], "score_2025": 21.70 },
      { "major_name": "Ngôn ngữ Hàn Quốc", "blocks": ["D01"], "score_2025": 21.50 },
      { "major_name": "Hóa dược", "blocks": ["A00", "B00"], "score_2025": 21.35 },
      { "major_name": "Ngôn ngữ Anh", "blocks": ["D01"], "score_2025": 21.35 },
      { "major_name": "Quản trị nhân lực", "blocks": ["A01", "D01"], "score_2025": 21.25 },
      { "major_name": "Kinh tế đầu tư", "blocks": ["A01", "D01"], "score_2025": 21.25 },
      { "major_name": "Hệ thống thông tin", "blocks": ["A00", "A01"], "score_2025": 21.10 },
      { "major_name": "Quản trị nhà hàng và dịch vụ ăn uống", "blocks": ["D01"], "score_2025": 20.85 },
      { "major_name": "Thiết kế thời trang", "blocks": ["D01"], "score_2025": 20.75 },
      { "major_name": "Tài chính - Ngân hàng", "blocks": ["A01", "D01"], "score_2025": 20.75 },
      { "major_name": "Công nghệ kỹ thuật điện tử y sinh", "blocks": ["A00", "A01"], "score_2025": 20.60 },
      { "major_name": "Công nghệ thực phẩm", "blocks": ["A00", "B00"], "score_2025": 20.60 },
      { "major_name": "Quản trị kinh doanh", "blocks": ["A01", "D01"], "score_2025": 20.25 },
      { "major_name": "Công nghệ kỹ thuật hóa học", "blocks": ["A00", "B00"], "score_2025": 20.25 },
      { "major_name": "Kế toán", "blocks": ["A01", "D01"], "score_2025": 20.00 },
      { "major_name": "Công nghệ kỹ thuật môi trường", "blocks": ["A00", "B00"], "score_2025": 18.75 }
    ]
  },
  {
    "code": "QSB",
    "name": "Đại học Bách Khoa - ĐHQG TP.HCM (HCMUT)",
    "scale": 100,
    "method": "Điểm Xét tuyển Tổng hợp (Thang 100)",
    "majors": [
      { "major_name": "Khoa học Máy tính", "blocks": ["A00", "A01"], "score_2025": 85.41 },
      { "major_name": "Khoa học Dữ liệu", "blocks": ["A00", "A01"], "score_2025": 83.85 },
      { "major_name": "Kỹ thuật Máy tính", "blocks": ["A00", "A01"], "score_2025": 82.91 },
      { "major_name": "Kỹ Thuật Cơ Điện tử", "blocks": ["A00", "A01"], "score_2025": 81.82 },
      { "major_name": "Điện - Điện tử - Viễn Thông - Tự động hoá - Thiết kế vi mạch", "blocks": ["A00", "A01"], "score_2025": 80.77 },
      { "major_name": "Logistics và Hệ thống Công nghiệp", "blocks": ["A00", "A01"], "score_2025": 80.52 },
      { "major_name": "Chương trình dạy và học bằng TA Kỹ thuật Hàng không", "blocks": ["A00", "A01"], "score_2025": 78.79 },
      { "major_name": "Vật lý Kỹ thuật", "blocks": ["A00", "A01"], "score_2025": 76.61 },
      { "major_name": "Kỹ thuật Ô tô", "blocks": ["A00", "A01"], "score_2025": 76.34 },
      { "major_name": "Cơ Kỹ thuật", "blocks": ["A00", "A01"], "score_2025": 75.98 },
      { "major_name": "Quản lý Công nghiệp", "blocks": ["A00", "A01", "D01"], "score_2025": 75.98 },
      { "major_name": "Kỹ Thuật Cơ khí", "blocks": ["A00", "A01"], "score_2025": 75.43 },
      { "major_name": "Hoá - Thực phẩm - Sinh học", "blocks": ["B00", "A00"], "score_2025": 75.43 },
      { "major_name": "Kỹ thuật Nhiệt", "blocks": ["A00", "A01"], "score_2025": 73.50 },
      { "major_name": "Kỹ thuật Vật liệu", "blocks": ["A00", "A01"], "score_2025": 71.10 },
      { "major_name": "Kiến Trúc", "blocks": ["A01", "V00"], "score_2025": 67.42 },
      { "major_name": "Bảo dưỡng Công nghiệp", "blocks": ["A00", "A01"], "score_2025": 65.59 },
      { "major_name": "Tài nguyên và Môi trường", "blocks": ["A00", "A01", "B00"], "score_2025": 60.93 },
      { "major_name": "Dệt - May", "blocks": ["A00", "A01"], "score_2025": 60.75 },
      { "major_name": "Dầu khí - Địa chất", "blocks": ["A00", "A01"], "score_2025": 60.00 },
      { "major_name": "Xây dựng và Quản lý Dự án Xây dựng", "blocks": ["A00", "A01"], "score_2025": 55.05 }
    ]
  },
  {
    "code": "PBH",
    "name": "Trường Sĩ quan Pháo binh",
    "scale": 30,
    "majors": [
      { "major_name": "Chỉ huy Tham mưu Pháo binh (miền Bắc)", "blocks": ["A00", "A01", "C01"], "score_2025": 24.40 },
      { "major_name": "Chỉ huy Tham mưu Pháo binh (miền Nam)", "blocks": ["A00", "A01", "C01"], "score_2025": 22.25 }
    ]
  },
  {
    "code": "TTH",
    "name": "Trường Sĩ quan Thông tin - Hệ quân sự (Đại học Thông tin Liên lạc)",
    "scale": 30,
    "majors": [
      { "major_name": "Chỉ huy - Tham mưu Thông tin (miền Bắc)", "blocks": ["A00", "A01", "C01", "X06"], "score_2025": 23.84 },
      { "major_name": "Chỉ huy - Tham mưu Thông tin (miền Nam)", "blocks": ["A00", "A01", "C01", "X06"], "score_2025": 22.75 }
    ]
  },
  {
    "code": "SNH",
    "name": "Trường Sĩ quan Công binh - Hệ quân sự (Đại học Ngô Quyền)",
    "scale": 30,
    "majors": [
      { "major_name": "Chỉ huy kỹ thuật Công binh (miền Bắc)", "blocks": ["A00", "A01"], "score_2025": 23.00 },
      { "major_name": "Chỉ huy kỹ thuật Công binh (miền Nam)", "blocks": ["A00", "A01"], "score_2025": 23.23 }
    ]
  },
  {
    "code": "TGH",
    "name": "Trường Sĩ quan Tăng thiết giáp",
    "scale": 30,
    "majors": [
      { "major_name": "Chỉ huy tham mưu Tăng Thiết giáp (Thí sinh nam miền Bắc)", "blocks": ["A00", "A01", "C01"], "score_2025": 24.05 },
      { "major_name": "Chỉ huy tham mưu Tăng Thiết giáp (Thí sinh nam miền Nam)", "blocks": ["A00", "A01", "C01"], "score_2025": 22.36 }
    ]
  }
  {
    "code": "YHB",
    "name": "Đại học Y Hà Nội",
    "scale": 30,
    "majors": [
      { "major_name": "Tâm lý học (Khối C00)", "blocks": ["C00"], "score_2025": 28.70 },
      { "major_name": "Y khoa", "blocks": ["B00"], "score_2025": 28.13 },
      { "major_name": "Răng - Hàm - Mặt", "blocks": ["B00"], "score_2025": 27.34 },
      { "major_name": "Tâm lý học (Khối D01)", "blocks": ["D01"], "score_2025": 26.70 },
      { "major_name": "Y khoa Phân hiệu Thanh Hóa", "blocks": ["B00"], "score_2025": 25.80 },
      { "major_name": "Kỹ thuật xét nghiệm y học", "blocks": ["A00", "B00"], "score_2025": 23.72 },
      { "major_name": "Tâm lý học (Khối B00)", "blocks": ["B00"], "score_2025": 23.70 },
      { "major_name": "Kỹ thuật hình ảnh y học", "blocks": ["A00", "B00"], "score_2025": 23.57 },
      { "major_name": "Y học cổ truyền", "blocks": ["A00", "B00"], "score_2025": 23.50 },
      { "major_name": "Khúc xạ nhãn khoa", "blocks": ["A00", "B00"], "score_2025": 23.23 },
      { "major_name": "Kỹ thuật phục hồi chức năng", "blocks": ["A00", "B00"], "score_2025": 22.50 },
      { "major_name": "Điều dưỡng", "blocks": ["A00", "B00"], "score_2025": 22.25 },
      { "major_name": "Kỹ thuật phục hình răng", "blocks": ["A00", "B00"], "score_2025": 21.85 },
      { "major_name": "Y tế công cộng (Khối D01)", "blocks": ["D01"], "score_2025": 21.20 },
      { "major_name": "Hộ sinh", "blocks": ["A00", "B00"], "score_2025": 20.35 },
      { "major_name": "Dinh dưỡng", "blocks": ["A00", "B00"], "score_2025": 18.75 },
      { "major_name": "Kỹ thuật xét nghiệm y học Phân hiệu Thanh Hóa", "blocks": ["A00", "B00"], "score_2025": 18.35 },
      { "major_name": "Y tế công cộng (Khối B00, B08)", "blocks": ["B00", "B08"], "score_2025": 18.20 },
      { "major_name": "Kỹ thuật phục hồi chức năng Phân hiệu Thanh Hóa", "blocks": ["A00", "B00"], "score_2025": 17.30 },
      { "major_name": "Y học dự phòng", "blocks": ["A00", "B00", "D07"], "score_2025": 17.00 },
      { "major_name": "Điều dưỡng Phân hiệu Thanh Hóa", "blocks": ["A00", "B00"], "score_2025": 17.00 },
      { "major_name": "Công tác xã hội", "blocks": ["A00", "B00", "B08"], "score_2025": 17.00 }
    ]
  },
  {
    "code": "YTB",
    "name": "Đại học Y Dược Thái Bình",
    "scale": 30,
    "majors": [
      { "major_name": "Y khoa", "blocks": ["B00", "D07", "D08"], "score_2025": 24.60 },
      { "major_name": "Dược học", "blocks": ["A00", "A01", "D07"], "score_2025": 19.50 },
      { "major_name": "Kỹ thuật xét nghiệm y học", "blocks": ["A00", "B00"], "score_2025": 19.50 },
      { "major_name": "Y học cổ truyền", "blocks": ["B00", "D08"], "score_2025": 19.00 },
      { "major_name": "Y học dự phòng", "blocks": ["B00", "D08"], "score_2025": 17.00 },
      { "major_name": "Điều dưỡng", "blocks": ["B00", "D08"], "score_2025": 17.00 }
    ]
  },
  {
    "code": "YPB",
    "name": "Đại học Y Dược Hải Phòng",
    "scale": 30,
    "majors": [
      { "major_name": "Y khoa", "blocks": ["A00", "B00"], "score_2025": 25.33 },
      { "major_name": "Răng - Hàm - Mặt", "blocks": ["B00"], "score_2025": 24.63 },
      { "major_name": "Y học cổ truyền", "blocks": ["B00"], "score_2025": 24.03 },
      { "major_name": "Kỹ thuật xét nghiệm y học", "blocks": ["B00"], "score_2025": 23.23 },
      { "major_name": "Điều dưỡng", "blocks": ["B00"], "score_2025": 22.22 },
      { "major_name": "Dược học", "blocks": ["A00", "B00", "D07"], "score_2025": 20.00 },
      { "major_name": "Y học dự phòng", "blocks": ["B00"], "score_2025": 19.35 }
    ]
  },
  {
    "code": "HYD",
    "name": "Học viện Y Dược học Cổ truyền Việt Nam",
    "scale": 30,
    "majors": [
      { "major_name": "Y khoa", "blocks": ["B00", "B03", "A02", "D08", "X14"], "score_2025": 24.25 },
      { "major_name": "Dược học", "blocks": ["A00", "B00", "D07", "C02", "X10"], "score_2025": 21.35 },
      { "major_name": "Y học cổ truyền", "blocks": ["B00", "B03", "A02", "D08", "X14"], "score_2025": 21.00 }
    ]
  },
  {
    "code": "DTY",
    "name": "Đại học Y Dược - Đại học Thái Nguyên",
    "scale": 30,
    "majors": [
      { "major_name": "Răng - Hàm - Mặt", "blocks": ["B00", "D07", "D08"], "score_2025": 26.15 },
      { "major_name": "Y khoa", "blocks": ["B00", "D07", "D08"], "score_2025": 25.85 },
      { "major_name": "Dược học", "blocks": ["A00", "A01", "A02", "B00", "D07", "D08"], "score_2025": 22.80 },
      { "major_name": "Kỹ thuật xét nghiệm y học", "blocks": ["A00", "A01", "A02", "B00", "D07", "D08"], "score_2025": 22.50 },
      { "major_name": "Kỹ thuật hình ảnh y học", "blocks": ["A00", "A01", "A02", "B00", "D07", "D08"], "score_2025": 21.25 },
      { "major_name": "Kỹ thuật phục hồi chức năng", "blocks": ["A00", "A01", "A02", "B00", "D07", "D08"], "score_2025": 20.50 },
      { "major_name": "Điều dưỡng", "blocks": ["B00", "D07", "D08"], "score_2025": 20.00 },
      { "major_name": "Y học dự phòng", "blocks": ["B00", "D07", "D08"], "score_2025": 18.30 }
    ]
  },
  {
    "code": "YKV",
    "name": "Đại học Y khoa Vinh",
    "scale": 30,
    "majors": [
      { "major_name": "Y khoa", "blocks": ["B00"], "score_2025": 22.10 },
      { "major_name": "Kỹ thuật xét nghiệm y học", "blocks": ["A00", "B00", "D07"], "score_2025": 20.00 },
      { "major_name": "Dược học", "blocks": ["A00", "B00"], "score_2025": 19.00 },
      { "major_name": "Điều dưỡng", "blocks": ["A00", "B00", "D07"], "score_2025": 17.50 },
      { "major_name": "Y học dự phòng", "blocks": ["A00", "B00", "D07"], "score_2025": 17.25 }
    ]
  }
]